MANIFEST.in
README.txt
setup.py
OASYS1_ShadowOui.egg-info/PKG-INFO
OASYS1_ShadowOui.egg-info/SOURCES.txt
OASYS1_ShadowOui.egg-info/dependency_links.txt
OASYS1_ShadowOui.egg-info/entry_points.txt
OASYS1_ShadowOui.egg-info/namespace_packages.txt
OASYS1_ShadowOui.egg-info/not-zip-safe
OASYS1_ShadowOui.egg-info/requires.txt
OASYS1_ShadowOui.egg-info/top_level.txt
orangecontrib/__init__.py
orangecontrib/shadow/__init__.py
orangecontrib/shadow/menu/__init__.py
orangecontrib/shadow/menu/ow_shadow_tools_menu.py
orangecontrib/shadow/test/__init__.py
orangecontrib/shadow/test/altissimo.py
orangecontrib/shadow/test/fresnel_zone_plate.py
orangecontrib/shadow/util/__init__.py
orangecontrib/shadow/util/python_script.py
orangecontrib/shadow/util/scanning_gui.py
orangecontrib/shadow/util/shadow_objects.py
orangecontrib/shadow/util/shadow_util.py
orangecontrib/shadow/util/undulator/__init__.py
orangecontrib/shadow/util/undulator/example2_ForShadowOui.py
orangecontrib/shadow/util/undulator/example_for_shadowoui.py
orangecontrib/shadow/util/undulator/source_undulator.py
orangecontrib/shadow/util/undulator/source_undulator_factory.py
orangecontrib/shadow/util/undulator/source_undulator_factory_pysru.py
orangecontrib/shadow/util/undulator/source_undulator_factory_srw.py
orangecontrib/shadow/util/undulator/source_undulator_input_output.py
orangecontrib/shadow/util/undulator/test_source_undulator.py
orangecontrib/shadow/util/undulator/test_source_undulator_factory.py
orangecontrib/shadow/widgets/__init__.py
orangecontrib/shadow/widgets/_not_used/__init__.py
orangecontrib/shadow/widgets/_not_used/ow_collimating_polycapillary.py
orangecontrib/shadow/widgets/_not_used/ow_focusing_polycapillary.py
orangecontrib/shadow/widgets/_under_developement/__init__.py
orangecontrib/shadow/widgets/_under_developement/ow_from_wofry_wavefront.py
orangecontrib/shadow/widgets/_under_developement/icons/from_wofry_wavefront_2d.png
orangecontrib/shadow/widgets/_under_developement/icons/wofry.png
orangecontrib/shadow/widgets/compound_optical_elements/__init__.py
orangecontrib/shadow/widgets/compound_optical_elements/ow_crl.py
orangecontrib/shadow/widgets/compound_optical_elements/ow_dcm.py
orangecontrib/shadow/widgets/compound_optical_elements/ow_kb.py
orangecontrib/shadow/widgets/compound_optical_elements/ow_lens.py
