Metadata-Version: 2.1
Name: OASYS1-ShadowOui
Version: 1.5.237
Summary: Shadow, Ray-tracing simulation software
Home-page: http://github.com/oasys-kit/ShadowOui
Download-URL: http://github.com/oasys-kit/ShadowOui
Author: Luca Rebuffi, Manuel Sanchez del Rio and Bioinformatics Laboratory, FRI UL
Author-email: lrebuffi@anl.gov
License: GPLv3
Keywords: ray-tracing,simulator,oasys1
Classifier: Development Status :: 5 - Production/Stable
Classifier: Environment :: X11 Applications :: Qt
Classifier: Environment :: Console
Classifier: Environment :: Plugins
Classifier: Programming Language :: Python :: 3
Classifier: Intended Audience :: Science/Research
Requires-Dist: shadow3>=23.9.19
Requires-Dist: oasys1>=1.2.145
Requires-Dist: syned-gui>=1.0.3
Requires-Dist: wofryshadow>=1.0.4
Requires-Dist: dabax
Requires-Dist: xoppylib>=1.0.21
Requires-Dist: shadow-hybrid-methods>=1.0.8
